viorina/__init__.py
viorina/descriptors/__init__.py
viorina/descriptors/descriptor_basics.py
viorina/descriptors/float_type.py
viorina/descriptors/integer_type.py
viorina/descriptors/text_type.py
viorina/payload_factory/__init__.py
viorina/payload_factory/viorina_base.py
viorina-2025.7.8.dist-info/METADATA
viorina-2025.7.8.dist-info/WHEEL
viorina-2025.7.8.dist-info/top_level.txt
viorina-2025.7.8.dist-info/RECORD
