Metadata-Version: 2.4
Name: viorina
Version: 2025.7.8
Summary: Light-weight minimal API Fuzzer in Python
Project-URL: Homepage, https://github.com/anzhi0708/viorina
Project-URL: Source, https://github.com/anzhi0708/viorina
Project-URL: Issues, https://github.com/anzhi0708/viorina/issues
Classifier: Development Status :: 3 - Alpha
Classifier: Intended Audience :: Developers
Classifier: License :: OSI Approved :: MIT License
Classifier: Programming Language :: Python :: 3.10
Classifier: Programming Language :: Python :: 3.11
Classifier: Programming Language :: Python :: 3.12
Classifier: Topic :: Software Development :: Testing
Classifier: Topic :: Software Development :: Quality Assurance
Classifier: Typing :: Typed
Requires-Python: >=3.12
Requires-Dist: regex-generate-py>=2023.3.7
